olek/__init__.py
olek/api.py
olek/middleware.py
olek/response.py
olek-0.1.dist-info/METADATA
olek-0.1.dist-info/WHEEL
olek-0.1.dist-info/top_level.txt
olek-0.1.dist-info/RECORD
